regression_model/VERSION
regression_model/__init__.py
regression_model/pipeline.py
regression_model/predict.py
regression_model/train_pipeline.py
regression_model/config/__init__.py
regression_model/config/config.py
regression_model/config/logging_config.py
regression_model/datasets/__init__.py
regression_model/datasets/test.csv
regression_model/processing/__init__.py
regression_model/processing/data_management.py
regression_model/processing/errors.py
regression_model/processing/get_weather_forecast.py
regression_model/processing/preprocessors.py
regression_model/processing/solar_calculation_functions.py
regression_model/processing/validation.py
regression_model/trained_models/__init__.py
regression_model/trained_models/rf_pipeline_output_v0.2.3.pkl
solar_prod_suvilahti_ml_model-0.2.3.dist-info/LICENSE
solar_prod_suvilahti_ml_model-0.2.3.dist-info/METADATA
solar_prod_suvilahti_ml_model-0.2.3.dist-info/WHEEL
solar_prod_suvilahti_ml_model-0.2.3.dist-info/top_level.txt
solar_prod_suvilahti_ml_model-0.2.3.dist-info/RECORD
