Metadata-Version: 2.1
Name: solar-prod-suvilahti-ml-model
Version: 0.2.3
Summary: Study project. A regression model to predict Solar Energy Production.
Home-page: https://github.com/screwdriver66/solar_prod_suvilahti
Author: Semen Uimonen
Author-email: simo.uimonen@gmail.com
License: GPLv3
Platform: UNKNOWN
Classifier: Development Status :: 4 - Beta
Classifier: License :: OSI Approved :: GNU General Public License v3 (GPLv3)
Classifier: Programming Language :: Python
Classifier: Programming Language :: Python :: 3
Classifier: Programming Language :: Python :: 3.6
Classifier: Programming Language :: Python :: 3.7
Classifier: Programming Language :: Python :: 3.8
Classifier: Programming Language :: Python :: Implementation :: CPython
Classifier: Programming Language :: Python :: Implementation :: PyPy
Requires-Python: >=3.6.0
Requires-Dist: numpy (<1.19.0,>=1.18.1)
Requires-Dist: pandas (<0.26.0,>=0.25.3)
Requires-Dist: scikit-learn (<0.23.0,>=0.22.1)
Requires-Dist: joblib (<0.15.0,>=0.14.1)
Requires-Dist: pytest (<6.0.0,>=5.3.2)
Requires-Dist: setuptools (<42.0.0,>=41.4.0)
Requires-Dist: wheel (<0.34.0,>=0.33.6)
Requires-Dist: fmi-weather (>=1.0.0)
Requires-Dist: twine (>=3.1.1)
